py_p_audio/__init__.py
py_p_audio/api.py
py_p_audio/core/__init__.py
py_p_audio/core/callbacks.py
py_p_audio/core/channels.py
py_p_audio/core/devices.py
py_p_audio/playback/__init__.py
py_p_audio/playback/asio.py
py_p_audio/playback/wasapi.py
py_p_audio/recording/__init__.py
py_p_audio/recording/asio.py
py_p_audio/recording/loopback.py
py_p_audio/recording/wasapi.py
py_p_audio/utils/__init__.py
py_p_audio/utils/exceptions.py
py_p_audio-1.0.1.dist-info/METADATA
py_p_audio-1.0.1.dist-info/WHEEL
py_p_audio-1.0.1.dist-info/entry_points.txt
py_p_audio-1.0.1.dist-info/top_level.txt
py_p_audio-1.0.1.dist-info/RECORD
