Metadata-Version: 2.4
Name: py-p-audio
Version: 1.0.1
Summary: Professional Python audio library with WASAPI/ASIO support for Windows
Author: hiroshi-tamura
License: MIT
Project-URL: Homepage, https://github.com/hiroshi-tamura/py-p-audio
Project-URL: Documentation, https://py-p-audio.readthedocs.io
Project-URL: Repository, https://github.com/hiroshi-tamura/py-p-audio.git
Project-URL: Issues, https://github.com/hiroshi-tamura/py-p-audio/issues
Keywords: audio,recording,playback,WASAPI,ASIO,loopback,Windows
Classifier: Development Status :: 5 - Production/Stable
Classifier: Intended Audience :: Developers
Classifier: Intended Audience :: End Users/Desktop
Classifier: License :: OSI Approved :: MIT License
Classifier: Operating System :: Microsoft :: Windows
Classifier: Programming Language :: Python :: 3.8
Classifier: Programming Language :: Python :: 3.9
Classifier: Programming Language :: Python :: 3.10
Classifier: Programming Language :: Python :: 3.11
Classifier: Programming Language :: Python :: 3.12
Classifier: Topic :: Multimedia :: Sound/Audio :: Capture/Recording
Classifier: Topic :: Multimedia :: Sound/Audio :: Players
Classifier: Topic :: Software Development :: Libraries :: Python Modules
Requires-Python: >=3.8
Requires-Dist: PyAudioWPatch>=0.2.12
Requires-Dist: sounddevice>=0.4.6
Requires-Dist: soundfile>=0.12.1
Requires-Dist: numpy>=1.21.0
Provides-Extra: dev
Requires-Dist: pytest>=7.0; extra == "dev"
Requires-Dist: black; extra == "dev"
Requires-Dist: ruff; extra == "dev"
Requires-Dist: mypy; extra == "dev"
Requires-Dist: pytest-cov; extra == "dev"
Provides-Extra: test
Requires-Dist: pytest>=7.0; extra == "test"
Requires-Dist: pytest-cov; extra == "test"
Requires-Dist: pytest-asyncio; extra == "test"
Provides-Extra: docs
Requires-Dist: sphinx; extra == "docs"
Requires-Dist: sphinx-rtd-theme; extra == "docs"
Requires-Dist: myst-parser; extra == "docs"
